{"frameRate":24,"name":"lan-ren","version":"5.5","compatibleVersion":"5.5","armature":[{"type":"Sheet","frameRate":24,"name":"Sprite","aabb":{"x":-250,"y":-250,"width":500,"height":500},"bone":[{"name":"root"}],"slot":[{"displayIndex":44,"name":"sheetSlot","parent":"root"}],"skin":[{"slot":[{"name":"sheetSlot","display":[{"name":"lan_0075_4"},{"name":"lan_0000_4-75"},{"name":"lan_0001_4-74"},{"name":"lan_0002_4-73"},{"name":"lan_0003_4-72"},{"name":"lan_0004_4-71"},{"name":"lan_0005_4-70"},{"name":"lan_0006_4-69"},{"name":"lan_0007_4-68"},{"name":"lan_0008_4-67"},{"name":"lan_0009_4-66"},{"name":"lan_0010_4-65"},{"name":"lan_0011_4-64"},{"name":"lan_0012_4-63"},{"name":"lan_0013_4-62"},{"name":"lan_0014_4-61"},{"name":"lan_0015_4-60"},{"name":"lan_0016_4-59"},{"name":"lan_0017_4-58"},{"name":"lan_0018_4-57"},{"name":"lan_0019_4-56"},{"name":"lan_0020_4-55"},{"name":"lan_0021_4-54"},{"name":"lan_0022_4-53"},{"name":"lan_0023_4-52"},{"name":"lan_0024_4-51"},{"name":"lan_0025_4-50"},{"name":"lan_0026_4-49"},{"name":"lan_0027_4-48"},{"name":"lan_0028_4-47"},{"name":"lan_0029_4-46"},{"name":"lan_0030_4-45"},{"name":"lan_0031_4-44"},{"name":"lan_0032_4-43"},{"name":"lan_0033_4-42"},{"name":"lan_0034_4-41"},{"name":"lan_0035_4-40"},{"name":"lan_0036_4-39"},{"name":"lan_0037_4-38"},{"name":"lan_0038_4-37"},{"name":"lan_0039_4-36"},{"name":"lan_0040_4-35"},{"name":"lan_0041_4-34"},{"name":"lan_0042_4-33"},{"name":"lan_0043_4-32"},{"name":"lan_0044_4-31"},{"name":"lan_0045_4-30"},{"name":"lan_0046_4-29"},{"name":"lan_0047_4-28"},{"name":"lan_0048_4-27"},{"name":"lan_0049_4-26"},{"name":"lan_0050_4-25"},{"name":"lan_0051_4-24"},{"name":"lan_0052_4-23"},{"name":"lan_0053_4-22"},{"name":"lan_0054_4-21"},{"name":"lan_0055_4-20"},{"name":"lan_0056_4-19"},{"name":"lan_0057_4-18"},{"name":"lan_0058_4-17"},{"name":"lan_0059_4-16"},{"name":"lan_0060_4-15"},{"name":"lan_0061_4-14"},{"name":"lan_0062_4-13"},{"name":"lan_0063_4-12"},{"name":"lan_0064_4-11"},{"name":"lan_0065_4-10"},{"name":"lan_0066_4-09"},{"name":"lan_0067_4-08"},{"name":"lan_0068_4-07"},{"name":"lan_0069_4-06"},{"name":"lan_0070_4-05"},{"name":"lan_0071_4-04"},{"name":"lan_0072_4-03"},{"name":"lan_0073_4-02"},{"name":"lan_0074_4-01"}]}]}],"animation":[{"duration":76,"playTimes":0,"name":"Sprite","slot":[{"name":"sheetSlot","displayFrame":[{},{"value":1},{"value":2},{"value":3},{"value":4},{"value":5},{"value":6},{"value":7},{"value":8},{"value":9},{"value":10},{"value":11},{"value":12},{"value":13},{"value":14},{"value":15},{"value":16},{"value":17},{"value":18},{"value":19},{"value":20},{"value":21},{"value":22},{"value":23},{"value":24},{"value":25},{"value":26},{"value":27},{"value":28},{"value":29},{"value":30},{"value":31},{"value":32},{"value":33},{"value":34},{"value":35},{"value":36},{"value":37},{"value":38},{"value":39},{"value":40},{"value":41},{"value":42},{"value":43},{"value":44},{"value":45},{"value":46},{"value":47},{"value":48},{"value":49},{"value":50},{"value":51},{"value":52},{"value":53},{"value":54},{"value":55},{"value":56},{"value":57},{"value":58},{"value":59},{"value":60},{"value":61},{"value":62},{"value":63},{"value":64},{"value":65},{"value":66},{"value":67},{"value":68},{"value":69},{"value":70},{"value":71},{"value":72},{"value":73},{"value":74},{"value":75}]}]}],"defaultActions":[{"gotoAndPlay":"Sprite"}]}]}